.gitignore
LICENSE
README.md
requirements.txt
setup.cfg
setup.py
ganapi/__init__.py
ganapi/api.py
ganapi/attribute.py
ganapi/attribute_manager.py
ganapi/contact.py
ganapi/contact_manager.py
ganapi/entity.py
ganapi/entity_manager.py
ganapi/fultest.py
ganapi/gan_exception.py
ganapi/helpers.py
ganapi/list.py
ganapi/list_manager.py
ganapi/report.py
ganapi/report_manager.py
ganapi/test_report_manager.py
ganapi.egg-info/PKG-INFO
ganapi.egg-info/SOURCES.txt
ganapi.egg-info/dependency_links.txt
ganapi.egg-info/requires.txt
ganapi.egg-info/top_level.txt
tests/__init__.py
tests/test_attribute_manager.py
tests/test_contact.py
tests/test_contact_manager.py
tests/test_entity.py
tests/test_list_manager.py