Metadata-Version: 1.1
Name: ganapi
Version: 0.1.0
Summary: Get a Newsletter REST API wrapper
Home-page: https://github.com/getanewsletter/api-python
Author: Get a Newsletter
Author-email: tech@getanewsletter.com
License: MIT
Download-URL: https://github.com/getanewsletter/api-python/tarball/v0.1.0
Keywords: Get a newsletter,ganapi
Platform: UNKNOWN
